polars_cache/__init__.py
polars_cache-1.0.5.dist-info/METADATA
polars_cache-1.0.5.dist-info/WHEEL
polars_cache-1.0.5.dist-info/RECORD
