Metadata-Version: 2.4
Name: polars-cache
Version: 1.0.5
Summary: A lightweight caching library for polars
Requires-Python: >=3.10
Requires-Dist: polars>=1.30.0
